README.md
setup.py
bigau_probability/Binomialdistribution.py
bigau_probability/Gaussiandistribution.py
bigau_probability/Generaldistribution.py
bigau_probability/__init__.py
bigau_probability.egg-info/PKG-INFO
bigau_probability.egg-info/SOURCES.txt
bigau_probability.egg-info/dependency_links.txt
bigau_probability.egg-info/not-zip-safe
bigau_probability.egg-info/top_level.txt