Metadata-Version: 2.1
Name: bigau_probability
Version: 3.0
Summary: Gaussian and Binomial distributions
Author: Grace Omotoso
Author-email: gracomot@gmail.com
